ecl_tools/__init__.py
ecl_tools/deployment.py
ecl_tools/metadata.py
ecl_tools/progress.py
ecl_tools/test.py
ecl_tools/utils.py
ecl_tools-1.0.1.dist-info/LICENSE
ecl_tools-1.0.1.dist-info/METADATA
ecl_tools-1.0.1.dist-info/NOTICE
ecl_tools-1.0.1.dist-info/WHEEL
ecl_tools-1.0.1.dist-info/top_level.txt
ecl_tools-1.0.1.dist-info/RECORD
